amqp_mock/__init__.py
amqp_mock/_message.py
amqp_mock/_mock_client.py
amqp_mock/_mock_server.py
amqp_mock/_storage.py
amqp_mock/_version.py
amqp_mock/py.typed
amqp_mock/amqp_server/__init__.py
amqp_mock/amqp_server/_amqp_connection.py
amqp_mock/amqp_server/_amqp_runner.py
amqp_mock/amqp_server/_amqp_server.py
amqp_mock/amqp_server/_amqp_site.py
amqp_mock/http_server/__init__.py
amqp_mock/http_server/_http_route.py
amqp_mock/http_server/_http_server.py
amqp_mock-0.6.2.dist-info/LICENSE.txt
amqp_mock-0.6.2.dist-info/METADATA
amqp_mock-0.6.2.dist-info/WHEEL
amqp_mock-0.6.2.dist-info/top_level.txt
amqp_mock-0.6.2.dist-info/RECORD
