Metadata-Version: 2.1
Name: amqp-mock
Version: 0.6.2
Summary: Remote AMQP mock
Home-page: https://github.com/tsv1/amqp-mock
Author: Nikita Tsvetkov
Author-email: tsv1@fastmail.com
License: Apache-2.0
Classifier: License :: OSI Approved :: Apache Software License
Classifier: Programming Language :: Python :: 3.8
Classifier: Programming Language :: Python :: 3.9
Classifier: Programming Language :: Python :: 3.10
Classifier: Programming Language :: Python :: 3.11
Classifier: Programming Language :: Python :: 3.12
Classifier: Typing :: Typed
Requires-Python: >=3.8.0
License-File: LICENSE.txt
Requires-Dist: aiohttp <4.0,>=3.5
Requires-Dist: pamqp <4.0,>=3.0
